iterpy/__init__.py
iterpy/_generate_pyi.py
iterpy/arr.py
iterpy/iter.py
iterpy/py.typed
iterpy/test_arr.py
iterpy/test_iter.py
iterpy-1.14.0.dist-info/licenses/LICENSE
iterpy-1.14.0.dist-info/METADATA
iterpy-1.14.0.dist-info/WHEEL
iterpy-1.14.0.dist-info/top_level.txt
iterpy-1.14.0.dist-info/RECORD
