Metadata-Version: 2.4
Name: iterpy
Version: 1.14.0
Summary: iterpy
Author-email: Martin Bernstorff <martinbernstorff@gmail.com>
License: MIT License
Project-URL: homepage, https://github.com/MartinBernstorff/iterpy
Project-URL: repository, https://github.com/MartinBernstorff/iterpy
Project-URL: documentation, https://MartinBernstorff.github.io/iterpy/
Classifier: Programming Language :: Python :: 3.9
Classifier: Programming Language :: Python :: 3.10
Classifier: Programming Language :: Python :: 3.11
Classifier: Programming Language :: Python :: 3.12
Requires-Python: >=3.9
License-File: LICENSE
Dynamic: license-file
